SpaGRD/__init__.py
SpaGRD/calculate_lr.py
SpaGRD/clr.py
SpaGRD/direction.py
SpaGRD/gft.py
SpaGRD/grd.py
SpaGRD/plot.py
SpaGRD/utils.py
spagrd-0.0.2.dist-info/METADATA
spagrd-0.0.2.dist-info/WHEEL
spagrd-0.0.2.dist-info/top_level.txt
spagrd-0.0.2.dist-info/RECORD
